[{"__symbolic":"module","version":3,"metadata":{"GroupComponent":{"__symbolic":"class","decorators":[{"__symbolic":"call","expression":{"__symbolic":"reference","module":"@angular/core","name":"Component"},"arguments":[{"selector":"ngx-query-group","template":"\n    <div class=\"col-md-12\">\n        <div class=\"form-group\">\n            <div class=\"col-md-3\">\n                <div class=\"input-group\">\n                    <div class=\"input-group-btn\">\n                        <button type=\"button\" class=\"btn btn-default\"\n                            (click)=\"addGroup()\"><i class=\"glyphicon glyphicon-plus\"></i> {{'{}'}}</button>\n                        <button type=\"button\" class=\"btn btn-default\"\n                            (click)=\"addRule()\"><i class=\"glyphicon glyphicon-plus\"></i></button>\n                        <button type=\"button\" class=\"btn btn-default\" *ngIf=\"canRemove\"\n                            (click)=\"removeGroup()\"><i class=\"glyphicon glyphicon-minus\"></i></button>\n                    </div>\n                    <select class=\"form-control\" [(ngModel)]=\"group.op\">\n                        <option *ngFor=\"let item of groupOps\" [ngValue]=\"item.key\">{{item.label}}</option>\n                    </select>\n                </div>\n            </div>\n        </div>\n    </div>\n    <div *ngIf=\"group.groups.length>0\" class=\"col-md-12 ngx-query-group-children\">\n        <ngx-query-group *ngFor=\"let group of group.groups\" [group]=\"group\"\n            [fields]=\"fields\" [canRemove]=\"true\" (remove)=\"removeGroupItem($event)\">\n        </ngx-query-group>\n    </div>\n    <div *ngIf=\"group.rules.length>0\" class=\"col-md-12 ngx-query-group-children\">\n        <ngx-query-rule *ngFor=\"let rule of group.rules\" [group]=\"group\" [rule]=\"rule\" [fields]=\"fields\">\n        </ngx-query-rule>\n    </div>\n    ","styles":["\n    .ngx-query-group-children {\n        margin-left:20px;\n    }"]}]}],"members":{"group":[{"__symbolic":"property","decorators":[{"__symbolic":"call","expression":{"__symbolic":"reference","module":"@angular/core","name":"Input"}}]}],"fields":[{"__symbolic":"property","decorators":[{"__symbolic":"call","expression":{"__symbolic":"reference","module":"@angular/core","name":"Input"}}]}],"canRemove":[{"__symbolic":"property","decorators":[{"__symbolic":"call","expression":{"__symbolic":"reference","module":"@angular/core","name":"Input"}}]}],"remove":[{"__symbolic":"property","decorators":[{"__symbolic":"call","expression":{"__symbolic":"reference","module":"@angular/core","name":"Output"}}]}],"__ctor__":[{"__symbolic":"constructor","parameters":[{"__symbolic":"reference","module":"../services/configuration.service","name":"QueryConfigurationService"}]}],"addGroup":[{"__symbolic":"method"}],"addRule":[{"__symbolic":"method"}],"removeGroup":[{"__symbolic":"method"}],"removeGroupItem":[{"__symbolic":"method"}]}}}},{"__symbolic":"module","version":1,"metadata":{"GroupComponent":{"__symbolic":"class","decorators":[{"__symbolic":"call","expression":{"__symbolic":"reference","module":"@angular/core","name":"Component"},"arguments":[{"selector":"ngx-query-group","template":"\n    <div class=\"col-md-12\">\n        <div class=\"form-group\">\n            <div class=\"col-md-3\">\n                <div class=\"input-group\">\n                    <div class=\"input-group-btn\">\n                        <button type=\"button\" class=\"btn btn-default\"\n                            (click)=\"addGroup()\"><i class=\"glyphicon glyphicon-plus\"></i> {{'{}'}}</button>\n                        <button type=\"button\" class=\"btn btn-default\"\n                            (click)=\"addRule()\"><i class=\"glyphicon glyphicon-plus\"></i></button>\n                        <button type=\"button\" class=\"btn btn-default\" *ngIf=\"canRemove\"\n                            (click)=\"removeGroup()\"><i class=\"glyphicon glyphicon-minus\"></i></button>\n                    </div>\n                    <select class=\"form-control\" [(ngModel)]=\"group.op\">\n                        <option *ngFor=\"let item of groupOps\" [ngValue]=\"item.key\">{{item.label}}</option>\n                    </select>\n                </div>\n            </div>\n        </div>\n    </div>\n    <div *ngIf=\"group.groups.length>0\" class=\"col-md-12 ngx-query-group-children\">\n        <ngx-query-group *ngFor=\"let group of group.groups\" [group]=\"group\"\n            [fields]=\"fields\" [canRemove]=\"true\" (remove)=\"removeGroupItem($event)\">\n        </ngx-query-group>\n    </div>\n    <div *ngIf=\"group.rules.length>0\" class=\"col-md-12 ngx-query-group-children\">\n        <ngx-query-rule *ngFor=\"let rule of group.rules\" [group]=\"group\" [rule]=\"rule\" [fields]=\"fields\">\n        </ngx-query-rule>\n    </div>\n    ","styles":["\n    .ngx-query-group-children {\n        margin-left:20px;\n    }"]}]}],"members":{"group":[{"__symbolic":"property","decorators":[{"__symbolic":"call","expression":{"__symbolic":"reference","module":"@angular/core","name":"Input"}}]}],"fields":[{"__symbolic":"property","decorators":[{"__symbolic":"call","expression":{"__symbolic":"reference","module":"@angular/core","name":"Input"}}]}],"canRemove":[{"__symbolic":"property","decorators":[{"__symbolic":"call","expression":{"__symbolic":"reference","module":"@angular/core","name":"Input"}}]}],"remove":[{"__symbolic":"property","decorators":[{"__symbolic":"call","expression":{"__symbolic":"reference","module":"@angular/core","name":"Output"}}]}],"__ctor__":[{"__symbolic":"constructor","parameters":[{"__symbolic":"reference","module":"../services/configuration.service","name":"QueryConfigurationService"}]}],"addGroup":[{"__symbolic":"method"}],"addRule":[{"__symbolic":"method"}],"removeGroup":[{"__symbolic":"method"}],"removeGroupItem":[{"__symbolic":"method"}]}}}}]